text2video/__init__.py
text2video/base.py
text2video/module.py
text2video-0.0.4.dist-info/METADATA
text2video-0.0.4.dist-info/WHEEL
text2video-0.0.4.dist-info/top_level.txt
text2video-0.0.4.dist-info/RECORD
